{
  "version": "tree-0.1",
  "tree": {
    "id": "App",
    "path": "",
    "children": {
      "Tree": {
        "id": "Tree",
        "path": "Tree",
        "constructInfo": {
          "fqn": "@aws-cdk/core.Construct",
          "version": "1.119.0"
        }
      },
      "SimpleStack": {
        "id": "SimpleStack",
        "path": "SimpleStack",
        "children": {
          "MyFirstCDKBucket": {
            "id": "MyFirstCDKBucket",
            "path": "SimpleStack/MyFirstCDKBucket",
            "children": {
              "Notifications": {
                "id": "Notifications",
                "path": "SimpleStack/MyFirstCDKBucket/Notifications",
                "constructInfo": {
                  "fqn": "@aws-cdk/core.Construct",
                  "version": "1.119.0"
                }
              },
              "Resource": {
                "id": "Resource",
                "path": "SimpleStack/MyFirstCDKBucket/Resource",
                "attributes": {
                  "aws:cdk:cloudformation:type": "AWS::S3::Bucket",
                  "aws:cdk:cloudformation:props": {
                    "bucketEncryption": {
                      "serverSideEncryptionConfiguration": [
                        {
                          "serverSideEncryptionByDefault": {
                            "sseAlgorithm": "AES256"
                          }
                        }
                      ]
                    }
                  }
                },
                "constructInfo": {
                  "fqn": "@aws-cdk/aws-s3.CfnBucket",
                  "version": "1.119.0"
                }
              }
            },
            "constructInfo": {
              "fqn": "@aws-cdk/aws-s3.Bucket",
              "version": "1.119.0"
            }
          },
          "MyFirstAppPhotos": {
            "id": "MyFirstAppPhotos",
            "path": "SimpleStack/MyFirstAppPhotos",
            "children": {
              "AwsCliLayer": {
                "id": "AwsCliLayer",
                "path": "SimpleStack/MyFirstAppPhotos/AwsCliLayer",
                "children": {
                  "Code": {
                    "id": "Code",
                    "path": "SimpleStack/MyFirstAppPhotos/AwsCliLayer/Code",
                    "children": {
                      "Stage": {
                        "id": "Stage",
                        "path": "SimpleStack/MyFirstAppPhotos/AwsCliLayer/Code/Stage",
                        "constructInfo": {
                          "fqn": "@aws-cdk/core.AssetStaging",
                          "version": "1.119.0"
                        }
                      },
                      "AssetBucket": {
                        "id": "AssetBucket",
                        "path": "SimpleStack/MyFirstAppPhotos/AwsCliLayer/Code/AssetBucket",
                        "children": {
                          "Notifications": {
                            "id": "Notifications",
                            "path": "SimpleStack/MyFirstAppPhotos/AwsCliLayer/Code/AssetBucket/Notifications",
                            "constructInfo": {
                              "fqn": "@aws-cdk/core.Construct",
                              "version": "1.119.0"
                            }
                          }
                        },
                        "constructInfo": {
                          "fqn": "@aws-cdk/aws-s3.BucketBase",
                          "version": "1.119.0"
                        }
                      }
                    },
                    "constructInfo": {
                      "fqn": "@aws-cdk/aws-s3-assets.Asset",
                      "version": "1.119.0"
                    }
                  },
                  "Resource": {
                    "id": "Resource",
                    "path": "SimpleStack/MyFirstAppPhotos/AwsCliLayer/Resource",
                    "attributes": {
                      "aws:cdk:cloudformation:type": "AWS::Lambda::LayerVersion",
                      "aws:cdk:cloudformation:props": {
                        "content": {
                          "s3Bucket": {
                            "Ref": "AssetParameterse9882ab123687399f934da0d45effe675ecc8ce13b40cb946f3e1d6141fe8d68S3BucketAEADE8C7"
                          },
                          "s3Key": {
                            "Fn::Join": [
                              "",
                              [
                                {
                                  "Fn::Select": [
                                    0,
                                    {
                                      "Fn::Split": [
                                        "||",
                                        {
                                          "Ref": "AssetParameterse9882ab123687399f934da0d45effe675ecc8ce13b40cb946f3e1d6141fe8d68S3VersionKeyE415415F"
                                        }
                                      ]
                                    }
                                  ]
                                },
                                {
                                  "Fn::Select": [
                                    1,
                                    {
                                      "Fn::Split": [
                                        "||",
                                        {
                                          "Ref": "AssetParameterse9882ab123687399f934da0d45effe675ecc8ce13b40cb946f3e1d6141fe8d68S3VersionKeyE415415F"
                                        }
                                      ]
                                    }
                                  ]
                                }
                              ]
                            ]
                          }
                        },
                        "description": "/opt/awscli/aws"
                      }
                    },
                    "constructInfo": {
                      "fqn": "@aws-cdk/aws-lambda.CfnLayerVersion",
                      "version": "1.119.0"
                    }
                  }
                },
                "constructInfo": {
                  "fqn": "@aws-cdk/lambda-layer-awscli.AwsCliLayer",
                  "version": "1.119.0"
                }
              },
              "CustomResourceHandler": {
                "id": "CustomResourceHandler",
                "path": "SimpleStack/MyFirstAppPhotos/CustomResourceHandler",
                "constructInfo": {
                  "fqn": "@aws-cdk/aws-lambda.SingletonFunction",
                  "version": "1.119.0"
                }
              },
              "Asset1": {
                "id": "Asset1",
                "path": "SimpleStack/MyFirstAppPhotos/Asset1",
                "children": {
                  "Stage": {
                    "id": "Stage",
                    "path": "SimpleStack/MyFirstAppPhotos/Asset1/Stage",
                    "constructInfo": {
                      "fqn": "@aws-cdk/core.AssetStaging",
                      "version": "1.119.0"
                    }
                  },
                  "AssetBucket": {
                    "id": "AssetBucket",
                    "path": "SimpleStack/MyFirstAppPhotos/Asset1/AssetBucket",
                    "children": {
                      "Notifications": {
                        "id": "Notifications",
                        "path": "SimpleStack/MyFirstAppPhotos/Asset1/AssetBucket/Notifications",
                        "constructInfo": {
                          "fqn": "@aws-cdk/core.Construct",
                          "version": "1.119.0"
                        }
                      }
                    },
                    "constructInfo": {
                      "fqn": "@aws-cdk/aws-s3.BucketBase",
                      "version": "1.119.0"
                    }
                  }
                },
                "constructInfo": {
                  "fqn": "@aws-cdk/aws-s3-assets.Asset",
                  "version": "1.119.0"
                }
              },
              "CustomResource": {
                "id": "CustomResource",
                "path": "SimpleStack/MyFirstAppPhotos/CustomResource",
                "children": {
                  "Default": {
                    "id": "Default",
                    "path": "SimpleStack/MyFirstAppPhotos/CustomResource/Default",
                    "constructInfo": {
                      "fqn": "@aws-cdk/core.CfnResource",
                      "version": "1.119.0"
                    }
                  }
                },
                "constructInfo": {
                  "fqn": "@aws-cdk/core.CustomResource",
                  "version": "1.119.0"
                }
              }
            },
            "constructInfo": {
              "fqn": "@aws-cdk/aws-s3-deployment.BucketDeployment",
              "version": "1.119.0"
            }
          },
          "AssetParameters": {
            "id": "AssetParameters",
            "path": "SimpleStack/AssetParameters",
            "children": {
              "e9882ab123687399f934da0d45effe675ecc8ce13b40cb946f3e1d6141fe8d68": {
                "id": "e9882ab123687399f934da0d45effe675ecc8ce13b40cb946f3e1d6141fe8d68",
                "path": "SimpleStack/AssetParameters/e9882ab123687399f934da0d45effe675ecc8ce13b40cb946f3e1d6141fe8d68",
                "children": {
                  "S3Bucket": {
                    "id": "S3Bucket",
                    "path": "SimpleStack/AssetParameters/e9882ab123687399f934da0d45effe675ecc8ce13b40cb946f3e1d6141fe8d68/S3Bucket",
                    "constructInfo": {
                      "fqn": "@aws-cdk/core.CfnParameter",
                      "version": "1.119.0"
                    }
                  },
                  "S3VersionKey": {
                    "id": "S3VersionKey",
                    "path": "SimpleStack/AssetParameters/e9882ab123687399f934da0d45effe675ecc8ce13b40cb946f3e1d6141fe8d68/S3VersionKey",
                    "constructInfo": {
                      "fqn": "@aws-cdk/core.CfnParameter",
                      "version": "1.119.0"
                    }
                  },
                  "ArtifactHash": {
                    "id": "ArtifactHash",
                    "path": "SimpleStack/AssetParameters/e9882ab123687399f934da0d45effe675ecc8ce13b40cb946f3e1d6141fe8d68/ArtifactHash",
                    "constructInfo": {
                      "fqn": "@aws-cdk/core.CfnParameter",
                      "version": "1.119.0"
                    }
                  }
                },
                "constructInfo": {
                  "fqn": "@aws-cdk/core.Construct",
                  "version": "1.119.0"
                }
              },
              "c24b999656e4fe6c609c31bae56a1cf4717a405619c3aa6ba1bc686b8c2c86cf": {
                "id": "c24b999656e4fe6c609c31bae56a1cf4717a405619c3aa6ba1bc686b8c2c86cf",
                "path": "SimpleStack/AssetParameters/c24b999656e4fe6c609c31bae56a1cf4717a405619c3aa6ba1bc686b8c2c86cf",
                "children": {
                  "S3Bucket": {
                    "id": "S3Bucket",
                    "path": "SimpleStack/AssetParameters/c24b999656e4fe6c609c31bae56a1cf4717a405619c3aa6ba1bc686b8c2c86cf/S3Bucket",
                    "constructInfo": {
                      "fqn": "@aws-cdk/core.CfnParameter",
                      "version": "1.119.0"
                    }
                  },
                  "S3VersionKey": {
                    "id": "S3VersionKey",
                    "path": "SimpleStack/AssetParameters/c24b999656e4fe6c609c31bae56a1cf4717a405619c3aa6ba1bc686b8c2c86cf/S3VersionKey",
                    "constructInfo": {
                      "fqn": "@aws-cdk/core.CfnParameter",
                      "version": "1.119.0"
                    }
                  },
                  "ArtifactHash": {
                    "id": "ArtifactHash",
                    "path": "SimpleStack/AssetParameters/c24b999656e4fe6c609c31bae56a1cf4717a405619c3aa6ba1bc686b8c2c86cf/ArtifactHash",
                    "constructInfo": {
                      "fqn": "@aws-cdk/core.CfnParameter",
                      "version": "1.119.0"
                    }
                  }
                },
                "constructInfo": {
                  "fqn": "@aws-cdk/core.Construct",
                  "version": "1.119.0"
                }
              },
              "dc53a013b16d192a39fa5491b05333eb2f49132fa0e784f194de2bf2382f6671": {
                "id": "dc53a013b16d192a39fa5491b05333eb2f49132fa0e784f194de2bf2382f6671",
                "path": "SimpleStack/AssetParameters/dc53a013b16d192a39fa5491b05333eb2f49132fa0e784f194de2bf2382f6671",
                "children": {
                  "S3Bucket": {
                    "id": "S3Bucket",
                    "path": "SimpleStack/AssetParameters/dc53a013b16d192a39fa5491b05333eb2f49132fa0e784f194de2bf2382f6671/S3Bucket",
                    "constructInfo": {
                      "fqn": "@aws-cdk/core.CfnParameter",
                      "version": "1.119.0"
                    }
                  },
                  "S3VersionKey": {
                    "id": "S3VersionKey",
                    "path": "SimpleStack/AssetParameters/dc53a013b16d192a39fa5491b05333eb2f49132fa0e784f194de2bf2382f6671/S3VersionKey",
                    "constructInfo": {
                      "fqn": "@aws-cdk/core.CfnParameter",
                      "version": "1.119.0"
                    }
                  },
                  "ArtifactHash": {
                    "id": "ArtifactHash",
                    "path": "SimpleStack/AssetParameters/dc53a013b16d192a39fa5491b05333eb2f49132fa0e784f194de2bf2382f6671/ArtifactHash",
                    "constructInfo": {
                      "fqn": "@aws-cdk/core.CfnParameter",
                      "version": "1.119.0"
                    }
                  }
                },
                "constructInfo": {
                  "fqn": "@aws-cdk/core.Construct",
                  "version": "1.119.0"
                }
              },
              "4502a4214e75439e7ae365c6a3f0d8680e41416f53107113dc96df133938b983": {
                "id": "4502a4214e75439e7ae365c6a3f0d8680e41416f53107113dc96df133938b983",
                "path": "SimpleStack/AssetParameters/4502a4214e75439e7ae365c6a3f0d8680e41416f53107113dc96df133938b983",
                "children": {
                  "S3Bucket": {
                    "id": "S3Bucket",
                    "path": "SimpleStack/AssetParameters/4502a4214e75439e7ae365c6a3f0d8680e41416f53107113dc96df133938b983/S3Bucket",
                    "constructInfo": {
                      "fqn": "@aws-cdk/core.CfnParameter",
                      "version": "1.119.0"
                    }
                  },
                  "S3VersionKey": {
                    "id": "S3VersionKey",
                    "path": "SimpleStack/AssetParameters/4502a4214e75439e7ae365c6a3f0d8680e41416f53107113dc96df133938b983/S3VersionKey",
                    "constructInfo": {
                      "fqn": "@aws-cdk/core.CfnParameter",
                      "version": "1.119.0"
                    }
                  },
                  "ArtifactHash": {
                    "id": "ArtifactHash",
                    "path": "SimpleStack/AssetParameters/4502a4214e75439e7ae365c6a3f0d8680e41416f53107113dc96df133938b983/ArtifactHash",
                    "constructInfo": {
                      "fqn": "@aws-cdk/core.CfnParameter",
                      "version": "1.119.0"
                    }
                  }
                },
                "constructInfo": {
                  "fqn": "@aws-cdk/core.Construct",
                  "version": "1.119.0"
                }
              }
            },
            "constructInfo": {
              "fqn": "@aws-cdk/core.Construct",
              "version": "1.119.0"
            }
          },
          "Custom::CDKBucketDeployment8693BB64968944B69AAFB0CC9EB8756C": {
            "id": "Custom::CDKBucketDeployment8693BB64968944B69AAFB0CC9EB8756C",
            "path": "SimpleStack/Custom::CDKBucketDeployment8693BB64968944B69AAFB0CC9EB8756C",
            "children": {
              "ServiceRole": {
                "id": "ServiceRole",
                "path": "SimpleStack/Custom::CDKBucketDeployment8693BB64968944B69AAFB0CC9EB8756C/ServiceRole",
                "children": {
                  "Resource": {
                    "id": "Resource",
                    "path": "SimpleStack/Custom::CDKBucketDeployment8693BB64968944B69AAFB0CC9EB8756C/ServiceRole/Resource",
                    "attributes": {
                      "aws:cdk:cloudformation:type": "AWS::IAM::Role",
                      "aws:cdk:cloudformation:props": {
                        "assumeRolePolicyDocument": {
                          "Statement": [
                            {
                              "Action": "sts:AssumeRole",
                              "Effect": "Allow",
                              "Principal": {
                                "Service": "lambda.amazonaws.com"
                              }
                            }
                          ],
                          "Version": "2012-10-17"
                        },
                        "managedPolicyArns": [
                          {
                            "Fn::Join": [
                              "",
                              [
                                "arn:",
                                {
                                  "Ref": "AWS::Partition"
                                },
                                ":iam::aws:policy/service-role/AWSLambdaBasicExecutionRole"
                              ]
                            ]
                          }
                        ]
                      }
                    },
                    "constructInfo": {
                      "fqn": "@aws-cdk/aws-iam.CfnRole",
                      "version": "1.119.0"
                    }
                  },
                  "DefaultPolicy": {
                    "id": "DefaultPolicy",
                    "path": "SimpleStack/Custom::CDKBucketDeployment8693BB64968944B69AAFB0CC9EB8756C/ServiceRole/DefaultPolicy",
                    "children": {
                      "Resource": {
                        "id": "Resource",
                        "path": "SimpleStack/Custom::CDKBucketDeployment8693BB64968944B69AAFB0CC9EB8756C/ServiceRole/DefaultPolicy/Resource",
                        "attributes": {
                          "aws:cdk:cloudformation:type": "AWS::IAM::Policy",
                          "aws:cdk:cloudformation:props": {
                            "policyDocument": {
                              "Statement": [
                                {
                                  "Action": [
                                    "s3:GetObject*",
                                    "s3:GetBucket*",
                                    "s3:List*"
                                  ],
                                  "Effect": "Allow",
                                  "Resource": [
                                    {
                                      "Fn::Join": [
                                        "",
                                        [
                                          "arn:",
                                          {
                                            "Ref": "AWS::Partition"
                                          },
                                          ":s3:::",
                                          {
                                            "Ref": "AssetParametersdc53a013b16d192a39fa5491b05333eb2f49132fa0e784f194de2bf2382f6671S3Bucket18015EBE"
                                          }
                                        ]
                                      ]
                                    },
                                    {
                                      "Fn::Join": [
                                        "",
                                        [
                                          "arn:",
                                          {
                                            "Ref": "AWS::Partition"
                                          },
                                          ":s3:::",
                                          {
                                            "Ref": "AssetParametersdc53a013b16d192a39fa5491b05333eb2f49132fa0e784f194de2bf2382f6671S3Bucket18015EBE"
                                          },
                                          "/*"
                                        ]
                                      ]
                                    }
                                  ]
                                },
                                {
                                  "Action": [
                                    "s3:GetObject*",
                                    "s3:GetBucket*",
                                    "s3:List*",
                                    "s3:DeleteObject*",
                                    "s3:PutObject",
                                    "s3:Abort*"
                                  ],
                                  "Effect": "Allow",
                                  "Resource": [
                                    {
                                      "Fn::GetAtt": [
                                        "MyFirstCDKBucketC899BE56",
                                        "Arn"
                                      ]
                                    },
                                    {
                                      "Fn::Join": [
                                        "",
                                        [
                                          {
                                            "Fn::GetAtt": [
                                              "MyFirstCDKBucketC899BE56",
                                              "Arn"
                                            ]
                                          },
                                          "/*"
                                        ]
                                      ]
                                    }
                                  ]
                                }
                              ],
                              "Version": "2012-10-17"
                            },
                            "policyName": "CustomCDKBucketDeployment8693BB64968944B69AAFB0CC9EB8756CServiceRoleDefaultPolicy88902FDF",
                            "roles": [
                              {
                                "Ref": "CustomCDKBucketDeployment8693BB64968944B69AAFB0CC9EB8756CServiceRole89A01265"
                              }
                            ]
                          }
                        },
                        "constructInfo": {
                          "fqn": "@aws-cdk/aws-iam.CfnPolicy",
                          "version": "1.119.0"
                        }
                      }
                    },
                    "constructInfo": {
                      "fqn": "@aws-cdk/aws-iam.Policy",
                      "version": "1.119.0"
                    }
                  }
                },
                "constructInfo": {
                  "fqn": "@aws-cdk/aws-iam.Role",
                  "version": "1.119.0"
                }
              },
              "Code": {
                "id": "Code",
                "path": "SimpleStack/Custom::CDKBucketDeployment8693BB64968944B69AAFB0CC9EB8756C/Code",
                "children": {
                  "Stage": {
                    "id": "Stage",
                    "path": "SimpleStack/Custom::CDKBucketDeployment8693BB64968944B69AAFB0CC9EB8756C/Code/Stage",
                    "constructInfo": {
                      "fqn": "@aws-cdk/core.AssetStaging",
                      "version": "1.119.0"
                    }
                  },
                  "AssetBucket": {
                    "id": "AssetBucket",
                    "path": "SimpleStack/Custom::CDKBucketDeployment8693BB64968944B69AAFB0CC9EB8756C/Code/AssetBucket",
                    "children": {
                      "Notifications": {
                        "id": "Notifications",
                        "path": "SimpleStack/Custom::CDKBucketDeployment8693BB64968944B69AAFB0CC9EB8756C/Code/AssetBucket/Notifications",
                        "constructInfo": {
                          "fqn": "@aws-cdk/core.Construct",
                          "version": "1.119.0"
                        }
                      }
                    },
                    "constructInfo": {
                      "fqn": "@aws-cdk/aws-s3.BucketBase",
                      "version": "1.119.0"
                    }
                  }
                },
                "constructInfo": {
                  "fqn": "@aws-cdk/aws-s3-assets.Asset",
                  "version": "1.119.0"
                }
              },
              "Resource": {
                "id": "Resource",
                "path": "SimpleStack/Custom::CDKBucketDeployment8693BB64968944B69AAFB0CC9EB8756C/Resource",
                "attributes": {
                  "aws:cdk:cloudformation:type": "AWS::Lambda::Function",
                  "aws:cdk:cloudformation:props": {
                    "code": {
                      "s3Bucket": {
                        "Ref": "AssetParametersc24b999656e4fe6c609c31bae56a1cf4717a405619c3aa6ba1bc686b8c2c86cfS3Bucket55EFA30C"
                      },
                      "s3Key": {
                        "Fn::Join": [
                          "",
                          [
                            {
                              "Fn::Select": [
                                0,
                                {
                                  "Fn::Split": [
                                    "||",
                                    {
                                      "Ref": "AssetParametersc24b999656e4fe6c609c31bae56a1cf4717a405619c3aa6ba1bc686b8c2c86cfS3VersionKey60329B70"
                                    }
                                  ]
                                }
                              ]
                            },
                            {
                              "Fn::Select": [
                                1,
                                {
                                  "Fn::Split": [
                                    "||",
                                    {
                                      "Ref": "AssetParametersc24b999656e4fe6c609c31bae56a1cf4717a405619c3aa6ba1bc686b8c2c86cfS3VersionKey60329B70"
                                    }
                                  ]
                                }
                              ]
                            }
                          ]
                        ]
                      }
                    },
                    "role": {
                      "Fn::GetAtt": [
                        "CustomCDKBucketDeployment8693BB64968944B69AAFB0CC9EB8756CServiceRole89A01265",
                        "Arn"
                      ]
                    },
                    "handler": "index.handler",
                    "layers": [
                      {
                        "Ref": "MyFirstAppPhotosAwsCliLayer1FD657AC"
                      }
                    ],
                    "runtime": "python3.6",
                    "timeout": 900
                  }
                },
                "constructInfo": {
                  "fqn": "@aws-cdk/aws-lambda.CfnFunction",
                  "version": "1.119.0"
                }
              }
            },
            "constructInfo": {
              "fqn": "@aws-cdk/aws-lambda.Function",
              "version": "1.119.0"
            }
          },
          "MyFirstCDKLambda": {
            "id": "MyFirstCDKLambda",
            "path": "SimpleStack/MyFirstCDKLambda",
            "children": {
              "ServiceRole": {
                "id": "ServiceRole",
                "path": "SimpleStack/MyFirstCDKLambda/ServiceRole",
                "children": {
                  "Resource": {
                    "id": "Resource",
                    "path": "SimpleStack/MyFirstCDKLambda/ServiceRole/Resource",
                    "attributes": {
                      "aws:cdk:cloudformation:type": "AWS::IAM::Role",
                      "aws:cdk:cloudformation:props": {
                        "assumeRolePolicyDocument": {
                          "Statement": [
                            {
                              "Action": "sts:AssumeRole",
                              "Effect": "Allow",
                              "Principal": {
                                "Service": "lambda.amazonaws.com"
                              }
                            }
                          ],
                          "Version": "2012-10-17"
                        },
                        "managedPolicyArns": [
                          {
                            "Fn::Join": [
                              "",
                              [
                                "arn:",
                                {
                                  "Ref": "AWS::Partition"
                                },
                                ":iam::aws:policy/service-role/AWSLambdaBasicExecutionRole"
                              ]
                            ]
                          }
                        ]
                      }
                    },
                    "constructInfo": {
                      "fqn": "@aws-cdk/aws-iam.CfnRole",
                      "version": "1.119.0"
                    }
                  },
                  "DefaultPolicy": {
                    "id": "DefaultPolicy",
                    "path": "SimpleStack/MyFirstCDKLambda/ServiceRole/DefaultPolicy",
                    "children": {
                      "Resource": {
                        "id": "Resource",
                        "path": "SimpleStack/MyFirstCDKLambda/ServiceRole/DefaultPolicy/Resource",
                        "attributes": {
                          "aws:cdk:cloudformation:type": "AWS::IAM::Policy",
                          "aws:cdk:cloudformation:props": {
                            "policyDocument": {
                              "Statement": [
                                {
                                  "Action": "s3:ListBucket",
                                  "Effect": "Allow",
                                  "Resource": {
                                    "Fn::GetAtt": [
                                      "MyFirstCDKBucketC899BE56",
                                      "Arn"
                                    ]
                                  }
                                },
                                {
                                  "Action": [
                                    "s3:GetObject",
                                    "s3:PutObject"
                                  ],
                                  "Effect": "Allow",
                                  "Resource": {
                                    "Fn::Join": [
                                      "",
                                      [
                                        {
                                          "Fn::GetAtt": [
                                            "MyFirstCDKBucketC899BE56",
                                            "Arn"
                                          ]
                                        },
                                        "/*"
                                      ]
                                    ]
                                  }
                                }
                              ],
                              "Version": "2012-10-17"
                            },
                            "policyName": "MyFirstCDKLambdaServiceRoleDefaultPolicyF25B7028",
                            "roles": [
                              {
                                "Ref": "MyFirstCDKLambdaServiceRoleA8AC7202"
                              }
                            ]
                          }
                        },
                        "constructInfo": {
                          "fqn": "@aws-cdk/aws-iam.CfnPolicy",
                          "version": "1.119.0"
                        }
                      }
                    },
                    "constructInfo": {
                      "fqn": "@aws-cdk/aws-iam.Policy",
                      "version": "1.119.0"
                    }
                  }
                },
                "constructInfo": {
                  "fqn": "@aws-cdk/aws-iam.Role",
                  "version": "1.119.0"
                }
              },
              "Code": {
                "id": "Code",
                "path": "SimpleStack/MyFirstCDKLambda/Code",
                "children": {
                  "Stage": {
                    "id": "Stage",
                    "path": "SimpleStack/MyFirstCDKLambda/Code/Stage",
                    "constructInfo": {
                      "fqn": "@aws-cdk/core.AssetStaging",
                      "version": "1.119.0"
                    }
                  },
                  "AssetBucket": {
                    "id": "AssetBucket",
                    "path": "SimpleStack/MyFirstCDKLambda/Code/AssetBucket",
                    "children": {
                      "Notifications": {
                        "id": "Notifications",
                        "path": "SimpleStack/MyFirstCDKLambda/Code/AssetBucket/Notifications",
                        "constructInfo": {
                          "fqn": "@aws-cdk/core.Construct",
                          "version": "1.119.0"
                        }
                      }
                    },
                    "constructInfo": {
                      "fqn": "@aws-cdk/aws-s3.BucketBase",
                      "version": "1.119.0"
                    }
                  }
                },
                "constructInfo": {
                  "fqn": "@aws-cdk/aws-s3-assets.Asset",
                  "version": "1.119.0"
                }
              },
              "Resource": {
                "id": "Resource",
                "path": "SimpleStack/MyFirstCDKLambda/Resource",
                "attributes": {
                  "aws:cdk:cloudformation:type": "AWS::Lambda::Function",
                  "aws:cdk:cloudformation:props": {
                    "code": {
                      "s3Bucket": {
                        "Ref": "AssetParameters4502a4214e75439e7ae365c6a3f0d8680e41416f53107113dc96df133938b983S3Bucket377B3053"
                      },
                      "s3Key": {
                        "Fn::Join": [
                          "",
                          [
                            {
                              "Fn::Select": [
                                0,
                                {
                                  "Fn::Split": [
                                    "||",
                                    {
                                      "Ref": "AssetParameters4502a4214e75439e7ae365c6a3f0d8680e41416f53107113dc96df133938b983S3VersionKeyAAB04B92"
                                    }
                                  ]
                                }
                              ]
                            },
                            {
                              "Fn::Select": [
                                1,
                                {
                                  "Fn::Split": [
                                    "||",
                                    {
                                      "Ref": "AssetParameters4502a4214e75439e7ae365c6a3f0d8680e41416f53107113dc96df133938b983S3VersionKeyAAB04B92"
                                    }
                                  ]
                                }
                              ]
                            }
                          ]
                        ]
                      }
                    },
                    "role": {
                      "Fn::GetAtt": [
                        "MyFirstCDKLambdaServiceRoleA8AC7202",
                        "Arn"
                      ]
                    },
                    "environment": {
                      "variables": {
                        "PHOTO_BUCKET_NAME": {
                          "Ref": "MyFirstCDKBucketC899BE56"
                        },
                        "AWS_NODEJS_CONNECTION_REUSE_ENABLED": "1"
                      }
                    },
                    "handler": "index.getPhotos",
                    "runtime": "nodejs14.x"
                  }
                },
                "constructInfo": {
                  "fqn": "@aws-cdk/aws-lambda.CfnFunction",
                  "version": "1.119.0"
                }
              }
            },
            "constructInfo": {
              "fqn": "@aws-cdk/aws-lambda-nodejs.NodejsFunction",
              "version": "1.119.0"
            }
          },
          "MyFirstCDKApi": {
            "id": "MyFirstCDKApi",
            "path": "SimpleStack/MyFirstCDKApi",
            "children": {
              "Resource": {
                "id": "Resource",
                "path": "SimpleStack/MyFirstCDKApi/Resource",
                "attributes": {
                  "aws:cdk:cloudformation:type": "AWS::ApiGatewayV2::Api",
                  "aws:cdk:cloudformation:props": {
                    "corsConfiguration": {
                      "allowMethods": [
                        "GET"
                      ],
                      "allowOrigins": [
                        "*"
                      ]
                    },
                    "name": "photo-api",
                    "protocolType": "HTTP"
                  }
                },
                "constructInfo": {
                  "fqn": "@aws-cdk/aws-apigatewayv2.CfnApi",
                  "version": "1.119.0"
                }
              },
              "DefaultStage": {
                "id": "DefaultStage",
                "path": "SimpleStack/MyFirstCDKApi/DefaultStage",
                "children": {
                  "Resource": {
                    "id": "Resource",
                    "path": "SimpleStack/MyFirstCDKApi/DefaultStage/Resource",
                    "attributes": {
                      "aws:cdk:cloudformation:type": "AWS::ApiGatewayV2::Stage",
                      "aws:cdk:cloudformation:props": {
                        "apiId": {
                          "Ref": "MyFirstCDKApi28C8ABE5"
                        },
                        "stageName": "$default",
                        "autoDeploy": true
                      }
                    },
                    "constructInfo": {
                      "fqn": "@aws-cdk/aws-apigatewayv2.CfnStage",
                      "version": "1.119.0"
                    }
                  }
                },
                "constructInfo": {
                  "fqn": "@aws-cdk/aws-apigatewayv2.HttpStage",
                  "version": "1.119.0"
                }
              },
              "GET--get-photos": {
                "id": "GET--get-photos",
                "path": "SimpleStack/MyFirstCDKApi/GET--get-photos",
                "children": {
                  "SimpleStackMyFirstCDKApiGETgetphotos5FCF9B98-Permission": {
                    "id": "SimpleStackMyFirstCDKApiGETgetphotos5FCF9B98-Permission",
                    "path": "SimpleStack/MyFirstCDKApi/GET--get-photos/SimpleStackMyFirstCDKApiGETgetphotos5FCF9B98-Permission",
                    "attributes": {
                      "aws:cdk:cloudformation:type": "AWS::Lambda::Permission",
                      "aws:cdk:cloudformation:props": {
                        "action": "lambda:InvokeFunction",
                        "functionName": {
                          "Fn::GetAtt": [
                            "MyFirstCDKLambda67A3AF76",
                            "Arn"
                          ]
                        },
                        "principal": "apigateway.amazonaws.com",
                        "sourceArn": {
                          "Fn::Join": [
                            "",
                            [
                              "arn:",
                              {
                                "Ref": "AWS::Partition"
                              },
                              ":execute-api:",
                              {
                                "Ref": "AWS::Region"
                              },
                              ":",
                              {
                                "Ref": "AWS::AccountId"
                              },
                              ":",
                              {
                                "Ref": "MyFirstCDKApi28C8ABE5"
                              },
                              "/*/*/get-photos"
                            ]
                          ]
                        }
                      }
                    },
                    "constructInfo": {
                      "fqn": "@aws-cdk/aws-lambda.CfnPermission",
                      "version": "1.119.0"
                    }
                  },
                  "HttpIntegration-adbeb5c8136f693925c55e84243c3438": {
                    "id": "HttpIntegration-adbeb5c8136f693925c55e84243c3438",
                    "path": "SimpleStack/MyFirstCDKApi/GET--get-photos/HttpIntegration-adbeb5c8136f693925c55e84243c3438",
                    "children": {
                      "Resource": {
                        "id": "Resource",
                        "path": "SimpleStack/MyFirstCDKApi/GET--get-photos/HttpIntegration-adbeb5c8136f693925c55e84243c3438/Resource",
                        "attributes": {
                          "aws:cdk:cloudformation:type": "AWS::ApiGatewayV2::Integration",
                          "aws:cdk:cloudformation:props": {
                            "apiId": {
                              "Ref": "MyFirstCDKApi28C8ABE5"
                            },
                            "integrationType": "AWS_PROXY",
                            "integrationUri": {
                              "Fn::GetAtt": [
                                "MyFirstCDKLambda67A3AF76",
                                "Arn"
                              ]
                            },
                            "payloadFormatVersion": "2.0"
                          }
                        },
                        "constructInfo": {
                          "fqn": "@aws-cdk/aws-apigatewayv2.CfnIntegration",
                          "version": "1.119.0"
                        }
                      }
                    },
                    "constructInfo": {
                      "fqn": "@aws-cdk/aws-apigatewayv2.HttpIntegration",
                      "version": "1.119.0"
                    }
                  },
                  "Resource": {
                    "id": "Resource",
                    "path": "SimpleStack/MyFirstCDKApi/GET--get-photos/Resource",
                    "attributes": {
                      "aws:cdk:cloudformation:type": "AWS::ApiGatewayV2::Route",
                      "aws:cdk:cloudformation:props": {
                        "apiId": {
                          "Ref": "MyFirstCDKApi28C8ABE5"
                        },
                        "routeKey": "GET /get-photos",
                        "authorizationType": "NONE",
                        "target": {
                          "Fn::Join": [
                            "",
                            [
                              "integrations/",
                              {
                                "Ref": "MyFirstCDKApiGETgetphotosHttpIntegrationadbeb5c8136f693925c55e84243c3438859A0E65"
                              }
                            ]
                          ]
                        }
                      }
                    },
                    "constructInfo": {
                      "fqn": "@aws-cdk/aws-apigatewayv2.CfnRoute",
                      "version": "1.119.0"
                    }
                  }
                },
                "constructInfo": {
                  "fqn": "@aws-cdk/aws-apigatewayv2.HttpRoute",
                  "version": "1.119.0"
                }
              }
            },
            "constructInfo": {
              "fqn": "@aws-cdk/aws-apigatewayv2.HttpApi",
              "version": "1.119.0"
            }
          },
          "MyFirstCDKBucketOutput": {
            "id": "MyFirstCDKBucketOutput",
            "path": "SimpleStack/MyFirstCDKBucketOutput",
            "constructInfo": {
              "fqn": "@aws-cdk/core.CfnOutput",
              "version": "1.119.0"
            }
          },
          "MyFirstCDKApiOutput": {
            "id": "MyFirstCDKApiOutput",
            "path": "SimpleStack/MyFirstCDKApiOutput",
            "constructInfo": {
              "fqn": "@aws-cdk/core.CfnOutput",
              "version": "1.119.0"
            }
          },
          "CDKMetadata": {
            "id": "CDKMetadata",
            "path": "SimpleStack/CDKMetadata",
            "children": {
              "Default": {
                "id": "Default",
                "path": "SimpleStack/CDKMetadata/Default",
                "constructInfo": {
                  "fqn": "@aws-cdk/core.CfnResource",
                  "version": "1.119.0"
                }
              },
              "Condition": {
                "id": "Condition",
                "path": "SimpleStack/CDKMetadata/Condition",
                "constructInfo": {
                  "fqn": "@aws-cdk/core.CfnCondition",
                  "version": "1.119.0"
                }
              }
            },
            "constructInfo": {
              "fqn": "@aws-cdk/core.Construct",
              "version": "1.119.0"
            }
          }
        },
        "constructInfo": {
          "fqn": "@aws-cdk/core.Stack",
          "version": "1.119.0"
        }
      }
    },
    "constructInfo": {
      "fqn": "@aws-cdk/core.App",
      "version": "1.119.0"
    }
  }
}